LICENSE
MANIFEST.in
README.rst
setup.py
PurePython/__init__.py
PurePython/main.py
PurePython.egg-info/PKG-INFO
PurePython.egg-info/SOURCES.txt
PurePython.egg-info/dependency_links.txt
PurePython.egg-info/top_level.txt